arthurai/__init__.py
arthurai/util.py
arthurai/version.py
arthurai/client/__init__.py
arthurai/client/auth.py
arthurai/client/client.py
arthurai/client/helper.py
arthurai/client/validation.py
arthurai/client/apiv3/__init__.py
arthurai/client/http/__init__.py
arthurai/client/http/arthur.py
arthurai/client/http/base.py
arthurai/client/http/requests.py
arthurai/common/__init__.py
arthurai/common/constants.py
arthurai/common/exceptions.py
arthurai/common/log.py
arthurai/core/__init__.py
arthurai/core/alerts.py
arthurai/core/attributes.py
arthurai/core/auth_info.py
arthurai/core/base.py
arthurai/core/data_service.py
arthurai/core/dataset_validation_utils.py
arthurai/core/decorators.py
arthurai/core/enrichment_status_waiter.py
arthurai/core/inferences.py
arthurai/core/model_status_waiter.py
arthurai/core/model_utils.py
arthurai/core/models.py
arthurai/core/status_waiter.py
arthurai/core/util.py
arthurai/core/bias/__init__.py
arthurai/core/bias/bias_metrics.py
arthurai/core/bias/bias_wrapper.py
arthurai/core/bias/threshold_mitigation.py
arthurai/core/viz/__init__.py
arthurai/core/viz/style.py
arthurai/core/viz/utils.py
arthurai/core/viz/visualizer.py
arthurai/datasets/__init__.py
arthurai/datasets/arthur_example.py
arthurai/datasets/download.py
arthurai/explainability/__init__.py
arthurai/explainability/arthur_explainer.py
arthurai/explainability/explanation_packager.py
arthurai/explainability/validation.py
docs/source/conf.py
docs/sphinx_ext/autosummary_permissions.py
tests/fixtures/__init__.py
tests/fixtures/mocks.py
tests/fixtures/models/multiclass.py
tests/fixtures/models/nlp.py
tests/fixtures/models/ranked_list.py
tests/fixtures/models/regression.py
tests/test_request_models/__init__.py
tests/test_request_models/fixtures.py
tests/test_request_models/test_alert_rule.py
tests/test_request_models/test_attribute_category.py
tests/test_request_models/test_model.py
arthurai-3.33.1.dist-info/METADATA
arthurai-3.33.1.dist-info/WHEEL
arthurai-3.33.1.dist-info/top_level.txt
arthurai-3.33.1.dist-info/RECORD
