Metadata-Version: 2.2
Name: arthurai
Version: 3.33.1
Summary: Arthur Python SDK
Author-email: Arthur <info@arthur.ai>
License: MIT
Project-URL: Arthur Homepage, https://arthur.ai
Project-URL: Documentation, https://docs.arthur.ai
Keywords: api arthur ArthurAI sdk ml model monitoring
Classifier: Development Status :: 5 - Production/Stable
Classifier: Intended Audience :: Developers
Classifier: Topic :: Software Development :: Libraries :: Application Frameworks
Classifier: License :: OSI Approved :: MIT License
Classifier: Programming Language :: Python :: 3.7
Classifier: Programming Language :: Python :: 3.8
Requires-Dist: dataclasses==0.7; python_version < "3.7"
Requires-Dist: dataclasses-json==0.4.5
Requires-Dist: dill<=0.3.3,>=0.3.1.1
Requires-Dist: docker<7,>=4.2.0
Requires-Dist: requests<=3,>=2.13.0
Requires-Dist: requests-toolbelt==0.9.1
Requires-Dist: numpy<=2,>=1.16.0
Requires-Dist: pandas<2,>=1.0.0
Requires-Dist: lime~=0.2.0.0
Requires-Dist: pyarrow<15,>=0.16.0
Requires-Dist: pyjwt~=2.6
Requires-Dist: python-dateutil<2.9,>=2.7.0
Requires-Dist: pytz>=2019.1
Requires-Dist: shap==0.41.0
Requires-Dist: shortuuid==1.0.1
Requires-Dist: seaborn<1,>=0.11.1
Requires-Dist: urllib3<2
Requires-Dist: yaspin>=2.3.0
